aws_cdk/aws_batch_alpha/__init__.py
aws_cdk/aws_batch_alpha/py.typed
aws_cdk/aws_batch_alpha/_jsii/__init__.py
aws_cdk/aws_batch_alpha/_jsii/aws-batch-alpha@2.95.1-alpha.0.jsii.tgz
aws_cdk.aws_batch_alpha-2.95.1a0.dist-info/LICENSE
aws_cdk.aws_batch_alpha-2.95.1a0.dist-info/METADATA
aws_cdk.aws_batch_alpha-2.95.1a0.dist-info/NOTICE
aws_cdk.aws_batch_alpha-2.95.1a0.dist-info/WHEEL
aws_cdk.aws_batch_alpha-2.95.1a0.dist-info/top_level.txt
aws_cdk.aws_batch_alpha-2.95.1a0.dist-info/RECORD
